LICENSE.txt
MANIFEST.in
README.md
run_tests.sh
setup.py
docs/Makefile
docs/conf.py
docs/index.rst
docs/javascript.rst
docs/migrating-0.9-to-1.0.rst
docs/using-fudge.rst
docs/why-fudge.rst
docs/_doctest_support/models.py
docs/_doctest_support/auth/__init__.py
docs/_doctest_support/oauthtwitter/__init__.py
docs/_static/.hidden
docs/api/fudge.inspector.rst
docs/api/fudge.patcher.rst
docs/api/fudge.rst
fudge/__init__.py
fudge/exc.py
fudge/inspector.py
fudge/patcher.py
fudge/util.py
fudge.egg-info/PKG-INFO
fudge.egg-info/SOURCES.txt
fudge.egg-info/dependency_links.txt
fudge.egg-info/top_level.txt
fudge/tests/__init__.py
fudge/tests/_py3_suite.py
fudge/tests/test_fudge.py
fudge/tests/test_import_all.py
fudge/tests/test_inspector.py
fudge/tests/test_inspector_import_all.py
fudge/tests/test_patcher.py
fudge/tests/test_registry.py
fudge/tests/support/__init__.py
fudge/tests/support/_for_patch.py
javascript/README.txt
javascript/fudge/fudge.js
javascript/fudge/testserver.py
javascript/fudge/tests/test_fudge.html
javascript/fudge/tests/test_fudge.js
javascript/fudge/tests/jquery/jquery-1.2.6.js
javascript/fudge/tests/jquery/qunit/testrunner.js