Metadata-Version: 1.1
Name: fudge
Version: 1.1.1
Summary: Replace real objects with fakes (mocks, stubs, etc) while testing.
Home-page: https://github.com/fudge-py/fudge
Author: Kumar McMillan
Author-email: kumar.mcmillan@gmail.com
License: The MIT License
Platform: UNKNOWN
Classifier: Intended Audience :: Developers
Classifier: Natural Language :: English
Classifier: Operating System :: OS Independent
Classifier: Programming Language :: Python :: 2
Classifier: Programming Language :: Python :: 3
Classifier: Programming Language :: Python :: 2.5
Classifier: Programming Language :: Python :: 2.6
Classifier: Programming Language :: Python :: 2.7
Classifier: Programming Language :: Python :: 3.1
Classifier: Programming Language :: Python :: 3.2
Classifier: Topic :: Software Development :: Testing
